README.md
setup.py
pulumi_genesiscloud/__init__.py
pulumi_genesiscloud/_inputs.py
pulumi_genesiscloud/_utilities.py
pulumi_genesiscloud/filesystem.py
pulumi_genesiscloud/floating_ip.py
pulumi_genesiscloud/images.py
pulumi_genesiscloud/instance.py
pulumi_genesiscloud/instance_status.py
pulumi_genesiscloud/outputs.py
pulumi_genesiscloud/provider.py
pulumi_genesiscloud/pulumi-plugin.json
pulumi_genesiscloud/py.typed
pulumi_genesiscloud/security_group.py
pulumi_genesiscloud/snapshot.py
pulumi_genesiscloud/ssh_key.py
pulumi_genesiscloud/volume.py
pulumi_genesiscloud.egg-info/PKG-INFO
pulumi_genesiscloud.egg-info/SOURCES.txt
pulumi_genesiscloud.egg-info/dependency_links.txt
pulumi_genesiscloud.egg-info/not-zip-safe
pulumi_genesiscloud.egg-info/requires.txt
pulumi_genesiscloud.egg-info/top_level.txt
pulumi_genesiscloud/config/__init__.py
pulumi_genesiscloud/config/vars.py