Metadata-Version: 2.1
Name: pulumi-genesiscloud
Version: 0.0.34
Summary: A Pulumi package for creating and managing genesiscloud cloud resources.
Home-page: https://www.pulumi.io
License: Apache-2.0
Project-URL: Repository, https://github.com/genesiscloud/pulumi-genesiscloud
Keywords: pulumi genesiscloud category/cloud
Platform: UNKNOWN
Requires-Python: >=3.8
